{
  "https://v.daum.net/v/20260713050155305": "호르무즈 재봉쇄 우려로 국내 해운·정유업계가 원유 수급과 해상운송 차질, 유가 변동성 확대에 대비",
  "https://v.daum.net/v/20260713060653322": "7~8월 도입분은 확보했지만 추가 계약이 필요한 9월 이후 중동산 원유 물량과 조달비용이 핵심 변수",
  "https://v.daum.net/v/20260713071150242": "미군이 호르무즈 민간선박 공격 능력 약화를 명분으로 이란 추가 공습에 나선 가운데 트럼프는 해협 개방을 주장",
  "https://v.daum.net/v/20260713125753248": "국내 정유사의 7~8월 원유 도입분이 전년 수준 이상 확보돼 단기 수급 차질 가능성은 낮다는 정부 판단",
  "https://v.daum.net/v/20260713163907337": "산업부는 단기 원유 수급 영향과 최고가격 조정 가능성에 선을 그으면서도 사태 장기화에 따른 공급 차질을 점검",
  "https://v.daum.net/v/20260713150439570": "정부가 원유 수급 긴급점검에 나선 가운데 정유업계는 9월 신규 도입분과 최고가격제 기준 논란을 우려",
  "https://v.daum.net/v/20260714060856106": "러시아 경유 수출 금지와 중동 정제시설 차질로 제품 마진이 뛰며 세계 5위 정제능력의 한국 정유사 수출 확대 기대",
  "https://v.daum.net/v/20260713205612812": "7~8월 원유는 전년 수준 이상 확보했지만 호르무즈 봉쇄 장기화 시 9월 이후 도입분과 국제유가가 위험 요인",
  "https://v.daum.net/v/20260713215959902": "정부와 정유업계는 당장 수급 문제가 없다고 보면서도 9월 이후 중동산 원유 조달 차질 가능성에 대비",
  "https://v.daum.net/v/20260714151750153": "러시아 경유 수출 제한과 중동 정제설비 차질로 윤활기유 가격·스프레드가 오르며 국내 정유사 수익성 개선 전망",
  "https://v.daum.net/v/20260714162907589": "국제유가 상승 기대에 WTI 원유선물 ETF가 일주일간 16.16% 오르는 등 원유 상품과 정유주가 동반 강세",
  "https://v.daum.net/v/20260714150358424": "호르무즈 이중봉쇄 재개로 고유가가 역래깅 부담은 낮췄지만 장기 공급불안이 정유·석화업계 하반기 변수로 부상",
  "https://v.daum.net/v/20260715074849087": "최고가격제와 수출 제한으로 정유 부문 수익성이 악화돼 주요 정유사의 2분기 영업이익이 전 분기보다 감소",
  "https://v.daum.net/v/20260715002746894": "호르무즈 통항 불확실성 재확대로 국제유가가 약 10% 뛰며 국내 원유 조달비와 최고가격제 부담이 확대",
  "https://v.daum.net/v/20260714172237147": "정유사들은 7~8월 물량을 확보했지만 해협 재봉쇄가 장기화하면 9월 이후 중동산 원유 도입 차질을 우려",
  "https://v.daum.net/v/20260715142413166": "유류세 인하가 정유사 이익을 키우고 탄소중립을 저해한다는 지적과 함께 취약계층 직접지원 전환 필요성 제기",
  "https://v.daum.net/v/20260715161327785": "일본 정부가 호르무즈 상황 악화에 대비해 나프타와 나프타 유래 석유화학제품의 수급 안정 대책을 검토",
  "https://v.daum.net/v/20260715161245752": "LH가 광주선운2지구에서 단독주택용지 2필지와 주유소용지 1필지 등 총 3필지를 공급",
  "https://v.daum.net/v/20260716070154709": "주유소 빙판에서 손님이 중상을 입었는데도 관리 책임을 부인한 사업주에게 업무상과실치상 형사책임 인정",
  "https://v.daum.net/v/20260715182527604": "탈탄소 투자 축소와 지정학 위험 누적으로 정유 업황이 구조적 강세기에 진입했다는 분석에 S-Oil 목표주가 상향",
  "https://v.daum.net/v/20260715170900331": "정부가 전세버스에도 경유 유가연동보조금을 지급해 차량 한 대당 월 25만원 수준의 유류비를 지원",
  "https://v.daum.net/v/20260716110852144": "중동·러시아 정유시설 타격과 폭염으로 세계 원유 처리량이 하루 840만배럴 줄어 휘발유 가격 강세가 지속",
  "https://v.daum.net/v/20260716164953236": "울산 북항 LNG터미널 3단계 준공으로 21.5만㎘의 저장용량이 추가돼 국내 LNG 저장·공급 기반 확대",
  "https://v.daum.net/v/20260716101931285": "윤활기유 가격 상승과 정제마진 개선 기대가 겹치며 SK이노베이션 등 정유주가 하락장에서도 강세",
  "https://v.daum.net/v/20260717073151744": "국제유가 재상승과 석유 최고가격제 장기화 가능성이 겹치며 정유사의 역래깅 이후 실적 부담이 지속될 전망",
  "https://v.daum.net/v/20260717072903707": "WTI가 0.8% 내린 배럴당 78.95달러로 숨고르기 했지만 중동 긴장과 호르무즈 수송 차질 위험은 지속",
  "https://v.daum.net/v/20260717044049306": "셰브론이 호르무즈를 우회할 수 있는 이라크 남부 유전 2곳 개발 참여를 추진하며 대체 원유 확보에 나섬",
  "https://v.daum.net/v/20260717151550534": "호르무즈 긴장과 국제유가 변동성 확대로 정부가 석유 최고가격제의 종료 시점과 출구전략을 정하기 어려워짐",
  "https://v.daum.net/v/20260717140050391": "호르무즈 통항 차질에 홍해 봉쇄 우려까지 더해지며 중동 원유의 주요 해상 수송로가 동시에 막힐 위험 확대",
  "https://v.daum.net/v/20260717143454810": "미국 해상봉쇄 재개 첫날 호르무즈 통항 선박이 13척으로 줄어 전쟁 전의 10분의 1 수준까지 급감",
  "https://v.daum.net/v/20260720064658711": "정유사 2분기 실적은 전 분기보다 줄 전망이지만 높은 정제마진이 감소 폭을 제한할 것으로 예상",
  "https://v.daum.net/v/20260720074252879": "미국·이란 충돌 격화로 브렌트유가 6월 11일 이후 처음 배럴당 90달러를 다시 돌파",
  "https://v.daum.net/v/20260719172337297": "우크라이나 드론 공격으로 러시아 정유시설 가동이 멈추며 글로벌 디젤 공급난과 가격 상승 우려 확대",
  "https://v.daum.net/v/20260720155240179": "정유업계 2분기 실적은 감소할 전망이나 높은 정제마진과 재고평가 효과가 수익성 하락을 방어",
  "https://v.daum.net/v/20260720105856243": "호르무즈와 홍해 항로가 동시에 막히면 국제유가·국내 기름값 급등과 산업 전반의 비용 충격이 불가피",
  "https://v.daum.net/v/20260720155907519": "중동 생산 차질로 그룹3 윤활기유 가격이 톤당 4000달러에 육박해 국내 정유사의 실적 방어 요인으로 작용",
  "https://v.daum.net/v/20260721060455814": "정부가 7차 최고가격제로 휘발유·경유·등유 상한을 ℓ당 150원 낮췄지만 유가 재상승으로 출구 셈법이 복잡",
  "https://v.daum.net/v/20260721040139389": "중동 리스크로 그룹3 윤활기유 가격이 톤당 4000달러에 육박하며 국내 정유사의 역대급 수출 실적을 견인",
  "https://v.daum.net/v/20260720181128036": "브렌트유 9월물이 3.12% 오른 배럴당 90.85달러에 거래되며 90달러대 고유가가 다시 현실화",
  "https://v.daum.net/v/20260721160736413": "정유업계는 단기 물량은 확보했지만 전쟁 장기화 시 올해 3~4월과 같은 원유 수급 대란 재발을 우려",
  "https://v.daum.net/v/20260721142527568": "이재명 대통령이 국제유가 재상승을 이유로 석유 최고가격제 연장 필요성을 제기해 정책 지속 여부가 쟁점",
  "https://v.daum.net/v/20260721155609774": "국내 정유사들이 원유 수입선을 다변화한 덕분에 이란 전쟁 장기화 속에서도 당장의 수급 불안을 피함"
}
